idm/__init__.py
idm/__main__.py
idm/__version__.py
idm/idm.py
idm-0.57.data/data/LICENSE.rst
idm-0.57.data/data/README.md
idm-0.57.data/data/__version__.py
idm-0.57.dist-info/licenses/LICENSE.rst
idm-0.57.dist-info/METADATA
idm-0.57.dist-info/WHEEL
idm-0.57.dist-info/entry_points.txt
idm-0.57.dist-info/top_level.txt
idm-0.57.dist-info/RECORD
