Metadata-Version: 2.4
Name: idm
Version: 0.57
Summary: Downloader with Internet Download Manager (Windows)
Home-page: https://github.com/cumulus13/pyidm
Author: Hadi Cahyadi LD
Author-email: cumulus13@gmail.com
Maintainer: cumulus13 Team
Maintainer-email: cumulus13@gmail.com
License: GPL
Project-URL: Documentation, https://github.com/cumulus13/pyidm
Project-URL: Code, https://github.com/cumulus13/pyidm
Classifier: Development Status :: 5 - Production/Stable
Classifier: Intended Audience :: Developers
Classifier: License :: OSI Approved :: GNU General Public License (GPL)
Classifier: Operating System :: OS Independent
Classifier: Programming Language :: Python
Classifier: Programming Language :: Python :: 2
Classifier: Programming Language :: Python :: 2.7
Classifier: Programming Language :: Python :: 3
Requires-Python: >=2.7
License-File: LICENSE.rst
Requires-Dist: argparse
Requires-Dist: comtypes; platform_system == "Windows"
Requires-Dist: configset
Requires-Dist: pydebugger
Requires-Dist: make_colors
Provides-Extra: pyidm
Dynamic: author
Dynamic: author-email
Dynamic: classifier
Dynamic: description
Dynamic: description-content-type
Dynamic: home-page
Dynamic: license
Dynamic: license-file
Dynamic: maintainer
Dynamic: maintainer-email
Dynamic: project-url
Dynamic: provides-extra
Dynamic: requires-dist
Dynamic: requires-python
Dynamic: summary
